{
  "total_count": 4,
  "incomplete_results": false,
  "items": [
      {
          "login": "emiliano-ma",
          "id": 67980695,
          "node_id": "MDQ6VXNlcjY3OTgwNjk1",
          "avatar_url": "https://avatars3.githubusercontent.com/u/67980695?v=4",
          "gravatar_id": "",
          "url": "https://api.github.com/users/emiliano-ma",
          "html_url": "https://github.com/emiliano-ma",
          "followers_url": "https://api.github.com/users/emiliano-ma/followers",
          "following_url": "https://api.github.com/users/emiliano-ma/following{/other_user}",
          "gists_url": "https://api.github.com/users/emiliano-ma/gists{/gist_id}",
          "starred_url": "https://api.github.com/users/emiliano-ma/starred{/owner}{/repo}",
          "subscriptions_url": "https://api.github.com/users/emiliano-ma/subscriptions",
          "organizations_url": "https://api.github.com/users/emiliano-ma/orgs",
          "repos_url": "https://api.github.com/users/emiliano-ma/repos",
          "events_url": "https://api.github.com/users/emiliano-ma/events{/privacy}",
          "received_events_url": "https://api.github.com/users/emiliano-ma/received_events",
          "type": "User",
          "site_admin": false,
          "score": 1.0
      },
      {
          "login": "emiliano-maggioni",
          "id": 63653556,
          "node_id": "MDQ6VXNlcjYzNjUzNTU2",
          "avatar_url": "https://avatars2.githubusercontent.com/u/63653556?v=4",
          "gravatar_id": "",
          "url": "https://api.github.com/users/emiliano-maggioni",
          "html_url": "https://github.com/emiliano-maggioni",
          "followers_url": "https://api.github.com/users/emiliano-maggioni/followers",
          "following_url": "https://api.github.com/users/emiliano-maggioni/following{/other_user}",
          "gists_url": "https://api.github.com/users/emiliano-maggioni/gists{/gist_id}",
          "starred_url": "https://api.github.com/users/emiliano-maggioni/starred{/owner}{/repo}",
          "subscriptions_url": "https://api.github.com/users/emiliano-maggioni/subscriptions",
          "organizations_url": "https://api.github.com/users/emiliano-maggioni/orgs",
          "repos_url": "https://api.github.com/users/emiliano-maggioni/repos",
          "events_url": "https://api.github.com/users/emiliano-maggioni/events{/privacy}",
          "received_events_url": "https://api.github.com/users/emiliano-maggioni/received_events",
          "type": "User",
          "site_admin": false,
          "score": 1.0
      },
      {
          "login": "Emiliano-Manuel",
          "id": 20390312,
          "node_id": "MDQ6VXNlcjIwMzkwMzEy",
          "avatar_url": "https://avatars3.githubusercontent.com/u/20390312?v=4",
          "gravatar_id": "",
          "url": "https://api.github.com/users/Emiliano-Manuel",
          "html_url": "https://github.com/Emiliano-Manuel",
          "followers_url": "https://api.github.com/users/Emiliano-Manuel/followers",
          "following_url": "https://api.github.com/users/Emiliano-Manuel/following{/other_user}",
          "gists_url": "https://api.github.com/users/Emiliano-Manuel/gists{/gist_id}",
          "starred_url": "https://api.github.com/users/Emiliano-Manuel/starred{/owner}{/repo}",
          "subscriptions_url": "https://api.github.com/users/Emiliano-Manuel/subscriptions",
          "organizations_url": "https://api.github.com/users/Emiliano-Manuel/orgs",
          "repos_url": "https://api.github.com/users/Emiliano-Manuel/repos",
          "events_url": "https://api.github.com/users/Emiliano-Manuel/events{/privacy}",
          "received_events_url": "https://api.github.com/users/Emiliano-Manuel/received_events",
          "type": "User",
          "site_admin": false,
          "score": 1.0
      },
      {
          "login": "Emiliano-marquez",
          "id": 973792,
          "node_id": "MDQ6VXNlcjk3Mzc5Mg==",
          "avatar_url": "https://avatars1.githubusercontent.com/u/973792?v=4",
          "gravatar_id": "",
          "url": "https://api.github.com/users/Emiliano-marquez",
          "html_url": "https://github.com/Emiliano-marquez",
          "followers_url": "https://api.github.com/users/Emiliano-marquez/followers",
          "following_url": "https://api.github.com/users/Emiliano-marquez/following{/other_user}",
          "gists_url": "https://api.github.com/users/Emiliano-marquez/gists{/gist_id}",
          "starred_url": "https://api.github.com/users/Emiliano-marquez/starred{/owner}{/repo}",
          "subscriptions_url": "https://api.github.com/users/Emiliano-marquez/subscriptions",
          "organizations_url": "https://api.github.com/users/Emiliano-marquez/orgs",
          "repos_url": "https://api.github.com/users/Emiliano-marquez/repos",
          "events_url": "https://api.github.com/users/Emiliano-marquez/events{/privacy}",
          "received_events_url": "https://api.github.com/users/Emiliano-marquez/received_events",
          "type": "User",
          "site_admin": false,
          "score": 1.0
      }
  ]
}